nameko_eventlog_dispatcher/__init__.py
nameko_eventlog_dispatcher/eventlog_dispatcher.py
nameko_eventlog_dispatcher-0.4.2.dist-info/LICENSE
nameko_eventlog_dispatcher-0.4.2.dist-info/METADATA
nameko_eventlog_dispatcher-0.4.2.dist-info/WHEEL
nameko_eventlog_dispatcher-0.4.2.dist-info/top_level.txt
nameko_eventlog_dispatcher-0.4.2.dist-info/zip-safe
nameko_eventlog_dispatcher-0.4.2.dist-info/RECORD
