Metadata-Version: 2.1
Name: nameko-eventlog-dispatcher
Version: 0.4.2
Summary: Nameko dependency provider that dispatches log data using Events (Pub-Sub).
Home-page: https://github.com/sohonetlabs/nameko-eventlog-dispatcher
Author: Julio Trigo
Author-email: julio.trigo@sohonet.com
License: MIT License
Classifier: Intended Audience :: Developers
Classifier: License :: OSI Approved :: MIT License
Classifier: Operating System :: OS Independent
Classifier: Programming Language :: Python
Classifier: Programming Language :: Python :: 3
Classifier: Programming Language :: Python :: 3.6
Classifier: Programming Language :: Python :: 3.7
Classifier: Programming Language :: Python :: 3.8
Classifier: Programming Language :: Python :: 3.9
Classifier: Topic :: Internet
Classifier: Topic :: Software Development :: Libraries :: Python Modules
Requires-Python: >=3.6
License-File: LICENSE
Requires-Dist: nameko (>=2.6)
Provides-Extra: dev
Requires-Dist: pytest (<=4.3.0) ; extra == 'dev'
Requires-Dist: flake8 ; extra == 'dev'
Requires-Dist: coverage ; extra == 'dev'
Requires-Dist: restructuredtext-lint ; extra == 'dev'
Requires-Dist: Pygments ; extra == 'dev'
Requires-Dist: pytest-eventlet ; extra == 'dev'
